States/__init__.py
Covid_Data_Interface-1.dist-info/METADATA
Covid_Data_Interface-1.dist-info/WHEEL
Covid_Data_Interface-1.dist-info/top_level.txt
Covid_Data_Interface-1.dist-info/RECORD
