Metadata-Version: 2.1
Name: Covid-Data-Interface
Version: 1
Summary: Covid Data Interface for learning Python
Home-page: http://github.com/storborg/funniest
Author: Neil Aylor and Devon Schwartz
Author-email: neilaylor@hotmail.com
License: MIT
Platform: UNKNOWN
